[
	{
		"key": "dbln",
		"value": "%7B%2261576828958502%22%3A%22SLO1tLAk%22%7D",
		"domain": "facebook.com",
		"path": "/login/device-based/",
		"hostOnly": false,
		"creation": "2025-06-13T04:18:02.119Z",
		"lastAccessed": "2025-06-13T04:18:02.120Z"
	},
	{
		"key": "datr",
		"value": "NI1JaLdqO_OI0nUF8lJX8_sO",
		"domain": "facebook.com",
		"path": "/",
		"hostOnly": false,
		"creation": "2025-06-13T04:18:02.120Z",
		"lastAccessed": "2025-06-13T04:18:02.120Z"
	},
	{
		"key": "sb",
		"value": "NI1JaOoc_5Xzg_i6mmgdnWfb",
		"domain": "facebook.com",
		"path": "/",
		"hostOnly": false,
		"creation": "2025-06-13T04:18:02.120Z",
		"lastAccessed": "2025-06-13T04:18:02.120Z"
	},
	{
		"key": "c_user",
		"value": "61576828958502",
		"domain": "facebook.com",
		"path": "/",
		"hostOnly": false,
		"creation": "2025-06-13T04:18:02.120Z",
		"lastAccessed": "2025-06-13T04:18:02.120Z"
	},
	{
		"key": "xs",
		"value": "5%3ATYkc-dcyXh9bWA%3A2%3A1749651256%3A-1%3A-1",
		"domain": "facebook.com",
		"path": "/",
		"hostOnly": false,
		"creation": "2025-06-13T04:18:02.120Z",
		"lastAccessed": "2025-06-13T04:18:02.120Z"
	},
	{
		"key": "locale",
		"value": "en_US",
		"domain": "facebook.com",
		"path": "/",
		"hostOnly": false,
		"creation": "2025-06-13T04:18:02.120Z",
		"lastAccessed": "2025-06-13T04:18:02.120Z"
	},
	{
		"key": "fr",
		"value": "0QPjVmSkFzmGLBy7T.AWeZpgoVDfnbYRG6yskCXetZdmZh8YKTS6hgIouYOKxHI5_waRo.BoSY00..AAA.0.0.BoS6Zs.AWdBSr_VpZ27CGv4Mtsc_nycb0s",
		"domain": "facebook.com",
		"path": "/",
		"hostOnly": false,
		"creation": "2025-06-13T04:18:02.120Z",
		"lastAccessed": "2025-06-13T04:18:02.120Z"
	},
	{
		"key": "fbl_st",
		"value": "101033310%3BT%3A29163137",
		"domain": "facebook.com",
		"path": "/",
		"hostOnly": false,
		"creation": "2025-06-13T04:18:02.120Z",
		"lastAccessed": "2025-06-13T04:18:02.120Z"
	},
	{
		"key": "vpd",
		"value": "v1%3B696x360x2",
		"domain": "facebook.com",
		"path": "/",
		"hostOnly": false,
		"creation": "2025-06-13T04:18:02.120Z",
		"lastAccessed": "2025-06-13T04:18:02.120Z"
	},
	{
		"key": "wl_cbv",
		"value": "v2%3Bclient_version%3A2844%3Btimestamp%3A1749788268",
		"domain": "facebook.com",
		"path": "/",
		"hostOnly": false,
		"creation": "2025-06-13T04:18:02.120Z",
		"lastAccessed": "2025-06-13T04:18:02.120Z"
	}
]
