[
	{
		"key": "dbln",
		"value": "%7B%2261576828958502%22%3A%22SLO1tLAk%22%7D",
		"domain": "facebook.com",
		"path": "/login/device-based/",
		"hostOnly": false,
		"creation": "2025-06-12T17:12:44.256Z",
		"lastAccessed": "2025-06-12T17:12:44.258Z"
	},
	{
		"key": "datr",
		"value": "NI1JaLdqO_OI0nUF8lJX8_sO",
		"domain": "facebook.com",
		"path": "/",
		"hostOnly": false,
		"creation": "2025-06-12T17:12:44.258Z",
		"lastAccessed": "2025-06-12T17:12:44.258Z"
	},
	{
		"key": "sb",
		"value": "NI1JaOoc_5Xzg_i6mmgdnWfb",
		"domain": "facebook.com",
		"path": "/",
		"hostOnly": false,
		"creation": "2025-06-12T17:12:44.258Z",
		"lastAccessed": "2025-06-12T17:12:44.258Z"
	},
	{
		"key": "c_user",
		"value": "61576828958502",
		"domain": "facebook.com",
		"path": "/",
		"hostOnly": false,
		"creation": "2025-06-12T17:12:44.258Z",
		"lastAccessed": "2025-06-12T17:12:44.258Z"
	},
	{
		"key": "xs",
		"value": "5%3ATYkc-dcyXh9bWA%3A2%3A1749651256%3A-1%3A-1",
		"domain": "facebook.com",
		"path": "/",
		"hostOnly": false,
		"creation": "2025-06-12T17:12:44.258Z",
		"lastAccessed": "2025-06-12T17:12:44.258Z"
	},
	{
		"key": "locale",
		"value": "en_US",
		"domain": "facebook.com",
		"path": "/",
		"hostOnly": false,
		"creation": "2025-06-12T17:12:44.258Z",
		"lastAccessed": "2025-06-12T17:12:44.258Z"
	},
	{
		"key": "fr",
		"value": "0QPjVmSkFzmGLBy7T.AWdt0c8jo7aYU6IU8jyvijhGqiHLSpqdOBd_GzZsRKA0_o6kyFw.BoSY00..AAA.0.0.BoSwp2.AWcKypbZL5hMlhjeZUoo2P1-ihM",
		"domain": "facebook.com",
		"path": "/",
		"hostOnly": false,
		"creation": "2025-06-12T17:12:44.258Z",
		"lastAccessed": "2025-06-12T17:12:44.258Z"
	},
	{
		"key": "wl_cbv",
		"value": "v2%3Bclient_version%3A2843%3Btimestamp%3A1749748343",
		"domain": "facebook.com",
		"path": "/",
		"hostOnly": false,
		"creation": "2025-06-12T17:12:44.258Z",
		"lastAccessed": "2025-06-12T17:12:44.258Z"
	},
	{
		"key": "fbl_st",
		"value": "101036541%3BT%3A29162472",
		"domain": "facebook.com",
		"path": "/",
		"hostOnly": false,
		"creation": "2025-06-12T17:12:44.258Z",
		"lastAccessed": "2025-06-12T17:12:44.258Z"
	},
	{
		"key": "vpd",
		"value": "v1%3B760x360x2",
		"domain": "facebook.com",
		"path": "/",
		"hostOnly": false,
		"creation": "2025-06-12T17:12:44.258Z",
		"lastAccessed": "2025-06-12T17:12:44.258Z"
	}
                ]
